netbox_supervisor_plugin/__init__.py
netbox_supervisor_plugin/admin.py
netbox_supervisor_plugin/api/__init__.py
netbox_supervisor_plugin/api/serializers.py
netbox_supervisor_plugin/api/urls.py
netbox_supervisor_plugin/api/views.py
netbox_supervisor_plugin/apps.py
netbox_supervisor_plugin/choices.py
netbox_supervisor_plugin/filters.py
netbox_supervisor_plugin/forms.py
netbox_supervisor_plugin/migrations/0001_initial.py
netbox_supervisor_plugin/migrations/0002_metadata.py
netbox_supervisor_plugin/migrations/0003_sid_size.py
netbox_supervisor_plugin/migrations/0004_changelog.py
netbox_supervisor_plugin/migrations/0005_tenant_related_name.py
netbox_supervisor_plugin/migrations/0006_description.py
netbox_supervisor_plugin/migrations/0007_tenant_sid.py
netbox_supervisor_plugin/migrations/__init__.py
netbox_supervisor_plugin/models.py
netbox_supervisor_plugin/navigation.py
netbox_supervisor_plugin/supervisor.md
netbox_supervisor_plugin/tables.py
netbox_supervisor_plugin/template_content.py
netbox_supervisor_plugin/templates/netbox_supervisor_plugin/supervisor.html
netbox_supervisor_plugin/templates/netbox_supervisor_plugin/supervisor_edit.html
netbox_supervisor_plugin/templates/netbox_supervisor_plugin/supervisor_list.html
netbox_supervisor_plugin/templates/netbox_supervisor_plugin/supervisor_tenant.html
netbox_supervisor_plugin/templates/netbox_supervisor_plugin/supervisor_tenant_edit.html
netbox_supervisor_plugin/templates/netbox_supervisor_plugin/supervisor_tenant_left.html
netbox_supervisor_plugin/templates/netbox_supervisor_plugin/supervisor_tenant_list.html
netbox_supervisor_plugin/tests/__init__.py
netbox_supervisor_plugin/tests/test_api.py
netbox_supervisor_plugin/tests/test_models.py
netbox_supervisor_plugin/urls.py
netbox_supervisor_plugin/views.py
netbox_supervisor_plugin-1.0.0.dist-info/WHEEL
netbox_supervisor_plugin-1.0.0.dist-info/METADATA
netbox_supervisor_plugin-1.0.0.dist-info/RECORD
