Metadata-Version: 2.1
Name: netbox-supervisor-plugin
Version: 1.0.0
Summary: plugin for netbox
Author: Ilya Zakharov
Author-email: you@example.com
Requires-Python: >=3.7,<4.0
Classifier: Programming Language :: Python :: 3
Classifier: Programming Language :: Python :: 3.7
Classifier: Programming Language :: Python :: 3.8
Classifier: Programming Language :: Python :: 3.9
